{
  "id": "ga4--5-1",
  "moduleId": "5-1",
  "categoryId": "ga4",
  "title": "GA4の思想とデータモデル",
  "sections": [
    {
      "type": "intro",
      "data": {
        "content": "# なぜGA4はUAから変わったのか\n\n2023年7月、Googleはユニバーサルアナリティクス（UA）を終了し、GA4に完全移行しました。これはただのUIリニューアルではありません。**計測の思想が根本から変わった**のです。\n\n## UAの限界\n\nUAは「セッション」単位でデータを取得していました。\n\n- ユーザーがサイトに来る → セッション開始\n- ページを見る → ページビュー\n- 離脱 → セッション終了\n\nこのモデルは「Webサイト」のために作られていました。しかしビジネスは変わりました。\n\n**課題1**: スマホアプリとWebを横断する計測ができない\n**課題2**: 動画視聴・スクロール深度などの行動が取れない\n**課題3**: Cookieへの依存でプライバシー規制に対応できない\n\n## GA4が解決したこと\n\nGA4は「**イベント**」を唯一の計測単位にしました。\n\nページビューも、ボタンクリックも、購入も、すべて「イベント」として同じ形式で記録されます。これによりWeb・アプリを統一的に計測できるようになりました。\n\n**あなたへの問い**: 自社サイトでは今、どんなユーザー行動を計測できていますか？「ページビューだけ」なら、GA4のポテンシャルの10%も使えていません。",
        "diagram": false
      }
    },
    {
      "type": "concept",
      "data": {
        "content": "# イベントベースデータモデル\n\nGA4のすべてのデータは「イベント」を基本単位として構成されます。\n\n## GA4のデータ3層構造\n\nGA4のデータモデルは以下の3つの階層で成り立っています。\n\n### 1. ユーザー（User）\nサイトやアプリに訪問する個々の人物。ブラウザのCookieで識別される **user_pseudo_id**（匿名ID）と、ログイン時に設定できる **user_id** の2つのIDがあります。ユーザーには **ユーザープロパティ**（会員ランク、職種など）を付与できます。\n\n### 2. セッション（Session）\nユーザーの1回の訪問。**session_start** イベントで開始され、**ga_session_id** で識別されます。30分間操作がないとセッションが切れます（UAと同じ）。\n\n### 3. イベント（Event）\nユーザーの個々の行動。GA4では **すべてがイベント** です。\n\n```\nユーザー（user_pseudo_id: \"abc123\"）\n├── セッション1（ga_session_id: 111）\n│   ├── session_start\n│   ├── page_view（page_title: \"トップ\"）\n│   ├── scroll（percent_scrolled: 90）\n│   └── page_view（page_title: \"商品詳細\"）\n└── セッション2（ga_session_id: 222）\n    ├── session_start\n    ├── page_view（page_title: \"商品詳細\"）\n    ├── add_to_cart（item_name: \"Tシャツ\", price: 3980）\n    └── purchase（transaction_id: \"T-001\", value: 3980）\n```\n\n## イベントの構造\n\n各イベントは以下の要素で構成されます。\n\n```\nイベント（event）\n├── event_name: \"purchase\"           # 何が起きたか\n├── event_timestamp: 1234567890      # いつ起きたか\n└── event_params: [                  # どんな内容か\n      { key: \"transaction_id\", value: \"T-001\" },\n      { key: \"value\", value: 29800 },\n      { key: \"currency\", value: \"JPY\" }\n    ]\n```\n\n## UAとGA4の比較\n\n| 概念 | UA | GA4 |\n|------|-----|-----|\n| 計測単位 | セッション | **イベント** |\n| ページビュー | 独立したヒットタイプ | page_viewイベント |\n| 購入 | トランザクション（Enhanced Ecommerce） | purchaseイベント |\n| データ階層 | ユーザー > セッション > ヒット | ユーザー > セッション > **イベント** |\n| 行動の詳細 | カテゴリ/アクション/ラベル | **イベントパラメータ**（自由設計） |\n| BQ連携 | 有料（UA 360のみ） | **無料（BQ側のコストは別途）** |\n| Cookieレス対応 | 困難 | **設計済み（Consent Mode等）** |\n\n## BigQueryエクスポートの構造\n\nGA4のデータはBigQueryに以下の形で保存されます。\n\n```sql\n-- テーブル名: events_YYYYMMDD\nSELECT\n  event_name,\n  event_date,\n  (SELECT value.string_value\n   FROM UNNEST(event_params)\n   WHERE key = 'page_title') AS page_title,\n  user_pseudo_id\nFROM `project.dataset.events_*`\nWHERE event_name = 'page_view'\nLIMIT 10\n```\n\nBigQuery連携については後続のモジュールで詳しく学びます。ここではGA4のイベントデータがそのままSQLで分析できることを覚えておいてください。",
        "diagram": true
      }
    },
    {
      "type": "exercise",
      "data": {
        "content": "# 練習: ユーザー行動をGA4イベントモデルで表現する\n\n以下のユーザー行動シナリオを、GA4のイベントベースモデルで表現してください。\n\n## シナリオ\n\nあるECサイトで、ユーザーが以下の行動を取りました。\n\n1. トップページを閲覧した\n2. 検索バーで「ワイヤレスイヤホン」と検索した\n3. 「カートに追加」ボタンを押した（商品名: WH-1000XM5、価格: 44,000円）\n\n## 課題\n\n各行動のGA4イベントオブジェクトを完成させてください。\n`event_name`と`event_params`を正しく設定し、`classify`にイベント分類を記入してください。\n\n[▶ 実行] を押すと判定結果が表示されます。",
        "starterCode": "<!DOCTYPE html>\n<html lang=\"ja\">\n<head>\n  <meta charset=\"UTF-8\">\n  <title>GA4 イベントモデル練習</title>\n  <style>\n    body { font-family: sans-serif; padding: 20px; background: #f8fafc; }\n    .card { background: white; border-radius: 12px; padding: 16px; margin: 12px 0; box-shadow: 0 2px 8px rgba(0,0,0,0.1); }\n    .label { font-size: 12px; color: #64748b; font-weight: bold; }\n    .event-name { font-size: 18px; font-weight: bold; color: #0f172a; font-family: monospace; }\n    .classify { display: inline-block; padding: 2px 8px; border-radius: 8px; font-size: 12px; font-weight: bold; }\n    .auto { background: #dbeafe; color: #1d4ed8; }\n    .enhanced { background: #d1fae5; color: #065f46; }\n    .recommended { background: #fef3c7; color: #92400e; }\n    .custom { background: #ede9fe; color: #5b21b6; }\n    pre { background: #1e293b; color: #e2e8f0; padding: 12px; border-radius: 8px; overflow-x: auto; font-size: 13px; }\n    #result { margin-top: 20px; padding: 16px; border-radius: 12px; font-weight: bold; }\n    .ok { background: #d1fae5; color: #065f46; }\n    .ng { background: #fee2e2; color: #991b1b; }\n  </style>\n</head>\n<body>\n  <h2>GA4 イベントモデル練習</h2>\n  <p>各行動のイベントオブジェクトを完成させてください。</p>\n  <div id=\"events\"></div>\n  <div id=\"result\"></div>\n\n  <script>\n    // === ここを編集してください ===\n\n    // 行動1: トップページを閲覧した\n    const event1 = {\n      event_name: \"\",        // GA4のイベント名を入力\n      classify: \"\",          // 自動収集 / 拡張計測 / 推奨 / カスタム\n      event_params: {\n        // 主要パラメータを追加\n      }\n    };\n\n    // 行動2: 検索バーで「ワイヤレスイヤホン」と検索した\n    const event2 = {\n      event_name: \"\",\n      classify: \"\",\n      event_params: {\n        // 主要パラメータを追加\n      }\n    };\n\n    // 行動3: カートに追加（WH-1000XM5、44,000円）\n    const event3 = {\n      event_name: \"\",\n      classify: \"\",\n      event_params: {\n        // 主要パラメータを追加\n      }\n    };\n\n    // === ここから下は変更不要 ===\n    const events = [\n      { label: \"行動1: トップページ閲覧\", data: event1 },\n      { label: \"行動2: サイト内検索\", data: event2 },\n      { label: \"行動3: カートに追加\", data: event3 },\n    ];\n\n    const classMap = { \"自動収集\": \"auto\", \"拡張計測\": \"enhanced\", \"推奨\": \"recommended\", \"カスタム\": \"custom\" };\n\n    let html = \"\";\n    events.forEach(e => {\n      const cls = classMap[e.data.classify] || \"\";\n      html += '<div class=\"card\">';\n      html += '<div class=\"label\">' + e.label + '</div>';\n      html += '<div class=\"event-name\">' + (e.data.event_name || \"（未入力）\") + '</div>';\n      if (e.data.classify) html += ' <span class=\"classify ' + cls + '\">' + e.data.classify + '</span>';\n      html += '<pre>' + JSON.stringify(e.data.event_params, null, 2) + '</pre>';\n      html += '</div>';\n    });\n    document.getElementById(\"events\").innerHTML = html;\n\n    // 判定\n    let score = 0;\n    let total = 6;\n    let feedback = [];\n\n    if (event1.event_name === \"page_view\") { score++; } else { feedback.push(\"行動1: event_nameは page_view です\"); }\n    if (event1.classify === \"拡張計測\") { score++; } else { feedback.push(\"行動1: page_viewは「拡張計測」に分類されます（デフォルトONで自動送信）\"); }\n\n    if (event2.event_name === \"view_search_results\") { score++; } else { feedback.push(\"行動2: event_nameは view_search_results です\"); }\n    if (event2.classify === \"拡張計測\") { score++; } else { feedback.push(\"行動2: view_search_resultsは「拡張計測」です\"); }\n\n    if (event3.event_name === \"add_to_cart\") { score++; } else { feedback.push(\"行動3: event_nameは add_to_cart です\"); }\n    if (event3.classify === \"推奨\") { score++; } else { feedback.push(\"行動3: add_to_cartは「推奨」イベントです（手動実装が必要）\"); }\n\n    const pct = Math.round(score / total * 100);\n    const resultEl = document.getElementById(\"result\");\n    if (pct === 100) {\n      resultEl.className = \"ok\";\n      resultEl.textContent = \"🎉 全問正解！GA4のイベント分類を正しく理解しています。\";\n    } else if (pct >= 50) {\n      resultEl.className = \"ng\";\n      resultEl.innerHTML = \"💡 \" + score + \"/\" + total + \" 正解（\" + pct + \"%）<br><br>\" + feedback.join(\"<br>\");\n    } else {\n      resultEl.className = \"ng\";\n      resultEl.innerHTML = \"💪 \" + score + \"/\" + total + \" 正解<br><br>\" + feedback.join(\"<br>\");\n    }\n  </script>\n</body>\n</html>",
        "hints": [
          "ページ閲覧は page_view イベントです。拡張計測としてデフォルトONで自動送信されます。page_title と page_location が自動付与されます。",
          "サイト内検索は view_search_results（拡張計測）です。search_term パラメータに検索キーワードが入ります。コード不要で自動取得されます。",
          "カートに追加は add_to_cart（推奨イベント）です。手動実装が必要で、items 配列内に item_name, price を含めます。"
        ],
        "answer": "<!DOCTYPE html>\n<html lang=\"ja\">\n<head>\n  <meta charset=\"UTF-8\">\n  <title>GA4 イベントモデル練習 - 解答</title>\n  <style>\n    body { font-family: sans-serif; padding: 20px; background: #f8fafc; }\n    .card { background: white; border-radius: 12px; padding: 16px; margin: 12px 0; box-shadow: 0 2px 8px rgba(0,0,0,0.1); }\n    .label { font-size: 12px; color: #64748b; font-weight: bold; }\n    .event-name { font-size: 18px; font-weight: bold; color: #0f172a; font-family: monospace; }\n    .classify { display: inline-block; padding: 2px 8px; border-radius: 8px; font-size: 12px; font-weight: bold; }\n    .enhanced { background: #d1fae5; color: #065f46; }\n    .recommended { background: #fef3c7; color: #92400e; }\n    pre { background: #1e293b; color: #e2e8f0; padding: 12px; border-radius: 8px; overflow-x: auto; font-size: 13px; }\n    #result { margin-top: 20px; padding: 16px; border-radius: 12px; font-weight: bold; background: #d1fae5; color: #065f46; }\n  </style>\n</head>\n<body>\n  <h2>GA4 イベントモデル練習 - 模範解答</h2>\n  <div id=\"events\"></div>\n  <div id=\"result\"></div>\n\n  <script>\n    const event1 = {\n      event_name: \"page_view\",\n      classify: \"拡張計測\",\n      event_params: {\n        page_title: \"トップページ\",\n        page_location: \"https://example.com/\"\n      }\n    };\n\n    const event2 = {\n      event_name: \"view_search_results\",\n      classify: \"拡張計測\",\n      event_params: {\n        search_term: \"ワイヤレスイヤホン\"\n      }\n    };\n\n    const event3 = {\n      event_name: \"add_to_cart\",\n      classify: \"推奨\",\n      event_params: {\n        currency: \"JPY\",\n        value: 44000,\n        items: [{ item_name: \"WH-1000XM5\", price: 44000 }]\n      }\n    };\n\n    const events = [\n      { label: \"行動1: トップページ閲覧\", data: event1 },\n      { label: \"行動2: サイト内検索\", data: event2 },\n      { label: \"行動3: カートに追加\", data: event3 },\n    ];\n\n    const classMap = { \"拡張計測\": \"enhanced\", \"推奨\": \"recommended\" };\n    let html = \"\";\n    events.forEach(e => {\n      const cls = classMap[e.data.classify] || \"\";\n      html += '<div class=\"card\">';\n      html += '<div class=\"label\">' + e.label + '</div>';\n      html += '<div class=\"event-name\">' + e.data.event_name + '</div>';\n      html += ' <span class=\"classify ' + cls + '\">' + e.data.classify + '</span>';\n      html += '<pre>' + JSON.stringify(e.data.event_params, null, 2) + '</pre>';\n      html += '</div>';\n    });\n    document.getElementById(\"events\").innerHTML = html;\n\n    let score = 6, total = 6;\n    document.getElementById(\"result\").textContent = \"🎉 全問正解！GA4のイベント分類を正しく理解しています。\";\n  </script>\n</body>\n</html>"
      }
    },
    {
      "type": "quiz",
      "data": {
        "questions": [
          {
            "q": "GA4における「計測の基本単位」は何ですか？",
            "options": [
              "ページビュー",
              "セッション",
              "イベント",
              "ユーザー"
            ],
            "correct": 2,
            "explanation": "GA4ではページビューも購入も「イベント」として統一的に記録されます。これがUAとの最大の違いで、Web・アプリ横断の統一計測を可能にしています。"
          },
          {
            "q": "GA4のイベントに付加できる詳細情報（例: 商品名、価格）を何と呼ぶか？",
            "options": [
              "カスタムディメンション",
              "イベントパラメータ",
              "ユーザープロパティ",
              "セグメント"
            ],
            "correct": 1,
            "explanation": "「イベントパラメータ」はイベントに付加する詳細情報です。例えばpurchaseイベントに対して、transaction_id・value・currencyなどのパラメータを付加することで詳細な分析が可能になります。"
          },
          {
            "q": "GA4のBigQueryエクスポートについて正しいのはどれですか？",
            "options": [
              "有料プラン（GA4 360）でのみ利用できる",
              "無料で利用でき、生データにアクセスできる",
              "エクスポートできるのは集計データのみ",
              "BigQueryへのエクスポートはGTMが必要"
            ],
            "correct": 1,
            "explanation": "GA4のBigQueryエクスポートはUAと違い無料で利用できます。生のイベントデータにアクセスでき、SQLで柔軟に分析できるのがGA4の大きなメリットです。"
          }
        ]
      }
    },
    {
      "type": "summary",
      "data": {
        "content": "# モジュール5-1 完了！\n\nGA4の根幹となるデータモデルを理解しました。\n\n## 習得したスキル\n\n✅ **UAとGA4の根本的な違い**を説明できる\n✅ **イベントベースモデル**の3層構造（ユーザー > セッション > イベント）を理解した\n✅ **イベントの構成要素**（event_name / event_params）を説明できる\n✅ **ユーザー行動をGA4イベントに変換**する考え方を身につけた\n✅ **BigQueryエクスポート**の基本構造を把握した\n\n## なぜこれが重要か\n\nこの理解があると、今後のGA4設定・カスタムイベント設計・BigQuery分析のすべての基礎になります。「なんとなくGA4を使う」から「GA4の構造を理解して設計する」マーケターへの第一歩です。\n\n## 次のステップ\n\n次のモジュール **「5-2: GA4の初期設定と実装」** では、GA4プロパティの作成からgtag.js設置、拡張計測の有効化までを学びます。\n\n> 💡 **実務チャレンジ**: 自社のGA4管理画面でリアルタイムレポートを開き、イベント名の一覧を確認してみましょう。page_view、session_start以外に何のイベントが送られていますか？",
        "diagram": false
      }
    }
  ]
}
